pcao/__init__.py
pcao/chat.py
pcao-0.0.1.dist-info/LICENSE
pcao-0.0.1.dist-info/METADATA
pcao-0.0.1.dist-info/WHEEL
pcao-0.0.1.dist-info/RECORD
